{
  "id": "hn-20260701-000",
  "title": "Show HN: Bol.ai – Extract structured data from Bills of Lading",
  "source": "rss/hn",
  "source_url": "https://bol.ai/",
  "description": "Article URL: https://bol.ai/\nComments URL: https://news.ycombinator.com/item?id=48744342\nPoints: 1\n# Comments: 0",
  "summary": "Article URL: https://bol.ai/\nComments URL: https://news.ycombinator.com/item?id=48744342\nPoints: 1\n# Comments: 0",
  "tags": [
    "ai",
    "placeholder"
  ],
  "category": "AI Application",
  "status": "draft",
  "language": "",
  "stars": null,
  "authors": [
    ""
  ],
  "collected_at": "2026-07-01T18:27:41.441864+08:00",
  "analyzed_at": "2026-07-01T18:27:51.205435+08:00",
  "published_at": null,
  "innovation_score": null,
  "difficulty_score": null,
  "key_points": [],
  "risks": [],
  "raw_path": "Z:\\Users\\BVZ\\WorkSpace\\101Doodle\\VibeCoding\\ai-knowledge-base\\knowledge\\raw\\all-2026-07-01.json",
  "metadata": {
    "rss_source": "hn",
    "pub_date": "Wed, 01 Jul 2026 09:39:18 +0000"
  }
}